xIndices/__init__.py
xIndices/indices.py
xIndices/main.py
xIndices/preprocess_data.py
xIndices/utils.py
xIndices-1.2.1.dist-info/METADATA
xIndices-1.2.1.dist-info/WHEEL
xIndices-1.2.1.dist-info/top_level.txt
xIndices-1.2.1.dist-info/RECORD
